ddcCryptography/__init__.py
ddcCryptography/crypto.py
ddccryptography-1.0.13.dist-info/LICENSE
ddccryptography-1.0.13.dist-info/METADATA
ddccryptography-1.0.13.dist-info/WHEEL
ddccryptography-1.0.13.dist-info/RECORD
