Metadata-Version: 2.3
Name: ddcCryptography
Version: 1.0.13
Summary: Encode and Decode strings with Cryptography
License: MIT
Keywords: python3,python-3,python,cryptography,encode,encoder,decode,decoder,ddcCryptography
Author: Daniel Costa
Author-email: danieldcsta@gmail.com
Maintainer: Daniel Costa
Requires-Python: >=3.12,<4.0
Classifier: Development Status :: 5 - Production/Stable
Classifier: Environment :: Other Environment
Classifier: Intended Audience :: Developers
Classifier: License :: OSI Approved :: MIT License
Classifier: Natural Language :: English
Classifier: Operating System :: OS Independent
Classifier: Programming Language :: Python :: 3
Classifier: Programming Language :: Python :: 3.12
Classifier: Programming Language :: Python :: 3.13
Classifier: Topic :: Software Development :: Libraries :: Python Modules
Requires-Dist: cryptography (>=45.0.5,<46.0.0)
Project-URL: Homepage, https://pypi.org/project/ddcCryptography
Project-URL: Repository, https://github.com/ddc/ddcCryptography
